Metadata-Version: 2.4
Name: iflow-mcp_prashalruchiranga_arxiv-mcp-server
Version: 0.1.0
Summary: MCP server for accesing arXiv API
Author: Prashal Ruchiranga
License-Expression: MIT
Requires-Python: >=3.13
License-File: LICENSE
Requires-Dist: feedparser>=6.0.11
Requires-Dist: httpx>=0.28.1
Requires-Dist: mcp[cli]>=1.6.0
Requires-Dist: pymupdf>=1.25.5
Dynamic: license-file
